image_wrapper
