Metadata-Version: 2.1
Name: django-picsum
Version: 1.2
Summary: UNKNOWN
Home-page: https://github.com/VarthanV/django-picsum.git
Author: Vishnu Varthan Rao
Author-email: vishnulatha006@gmail.com
License: MIT License
Keywords: picsum,pixabay,django-pics,django image,django template
Platform: UNKNOWN
Classifier: Intended Audience :: Developers
Classifier: License :: OSI Approved :: MIT License
Classifier: Programming Language :: Python :: 3
Classifier: Programming Language :: Python :: 3.3
Classifier: Operating System :: OS Independent
Classifier: Topic :: Software Development :: Libraries
Classifier: Topic :: Utilities
Classifier: Environment :: Web Environment
Classifier: Framework :: Django
